README.rst
setup.py
django_mathjax/__init__.py
django_mathjax.egg-info/PKG-INFO
django_mathjax.egg-info/SOURCES.txt
django_mathjax.egg-info/dependency_links.txt
django_mathjax.egg-info/requires.txt
django_mathjax.egg-info/top_level.txt
django_mathjax/templatetags/__init__.py
django_mathjax/templatetags/mathjax.py